textocat/__init__.py
textocat/api.py
textocat/exceptions.py
textocat-0.1.0.dist-info/DESCRIPTION.rst
textocat-0.1.0.dist-info/METADATA
textocat-0.1.0.dist-info/metadata.json
textocat-0.1.0.dist-info/RECORD
textocat-0.1.0.dist-info/top_level.txt
textocat-0.1.0.dist-info/WHEEL
